alloai/__init__.py
alloai/cli.py
alloai/execute.py
alloai/parser.py
alloai-0.3.0.dist-info/licenses/LICENSE
alloai-0.3.0.dist-info/METADATA
alloai-0.3.0.dist-info/WHEEL
alloai-0.3.0.dist-info/entry_points.txt
alloai-0.3.0.dist-info/top_level.txt
alloai-0.3.0.dist-info/RECORD
