Metadata-Version: 2.4
Name: alloai
Version: 0.3.0
Summary: Write markdown files mixing Python code with natural language prompts that generate and execute additional code in a shared runtime
Home-page: https://github.com/m4xw311/AlloAI
Author: Maxwell Felix
Author-email: max@alloai.io
License: MIT
Project-URL: Homepage, https://github.com/m4xw311/AlloAI
Project-URL: Documentation, https://github.com/m4xw311/AlloAI#readme
Project-URL: Repository, https://github.com/m4xw311/AlloAI.git
Project-URL: Bug Tracker, https://github.com/m4xw311/AlloAI/issues
Keywords: llm,ai,markdown,code-execution,polyglot,scripting
Classifier: Development Status :: 3 - Alpha
Classifier: Intended Audience :: Developers
Classifier: Topic :: Software Development :: Libraries :: Python Modules
Classifier: Topic :: Scientific/Engineering :: Artificial Intelligence
Classifier: License :: OSI Approved :: MIT License
Classifier: Programming Language :: Python :: 3
Classifier: Programming Language :: Python :: 3.8
Classifier: Programming Language :: Python :: 3.9
Classifier: Programming Language :: Python :: 3.10
Classifier: Programming Language :: Python :: 3.11
Classifier: Programming Language :: Python :: 3.12
Classifier: Operating System :: OS Independent
Requires-Python: >=3.8
License-File: LICENSE
Requires-Dist: openai>=1.0.0
Requires-Dist: python-dotenv>=0.19.0
Requires-Dist: cloudpickle>=3.1.1
Provides-Extra: dev
Requires-Dist: pytest>=7.0.0; extra == "dev"
Requires-Dist: pytest-cov>=4.0.0; extra == "dev"
Requires-Dist: black>=22.0.0; extra == "dev"
Requires-Dist: flake8>=5.0.0; extra == "dev"
Requires-Dist: mypy>=0.990; extra == "dev"
Requires-Dist: build>=0.10.0; extra == "dev"
Requires-Dist: twine>=4.0.0; extra == "dev"
Dynamic: author-email
Dynamic: home-page
Dynamic: license-file
Dynamic: requires-python
